redis_relay.py
redis_relay-0.0.1.dist-info/LICENSE
redis_relay-0.0.1.dist-info/WHEEL
redis_relay-0.0.1.dist-info/METADATA
redis_relay-0.0.1.dist-info/RECORD
