Metadata-Version: 2.1
Name: redis-relay
Version: 0.0.1
Summary: redis relay for interprocess communication
Home-page: https://github.com/guyingbo/redis-relay
License: UNKNOWN
Keywords: aioredis pubsub
Author: Yingbo Gu
Author-email: tensiongyb@gmail.com
Maintainer: Yingbo Gu
Maintainer-email: tensiongyb@gmail.com
Requires-Python: >=3.5
Classifier: License :: OSI Approved :: MIT License
Classifier: Framework :: AsyncIO
Classifier: Intended Audience :: Developers
Classifier: Programming Language :: Python :: 3.5
Classifier: Programming Language :: Python :: 3.6
Classifier: Programming Language :: Python :: 3.7
Requires-Dist: aioredis
